[
  {
    "payload_uid": "c74df083-3d71-42da-963e-381b9b04b975",
    "number": "OE011799",
    "status": "Active",
    "category": "Overseas Entity",
    "country_of_origin": "SAINT LUCIA",
    "sic_code_sic_text_1": "None Supplied",
    "name": "ASHMORE INVESTMENTS LIMITED",
    "sic_code_sic_text_2": "",
    "sic_code_sic_text_3": "",
    "sic_code_sic_text_4": "",
    "uid": "9259d894-ae44-410c-b51a-89e6be105e95",
    "created_at": "2025-11-04 14:15:49.846752",
    "registered_address_country": "SAINT LUCIA",
    "alpha_2_country_code_registered_address_country": "LC",
    "alpha_2_country_code_country_of_origin": "LC"
  },
  {
    "payload_uid": "c74df083-3d71-42da-963e-381b9b04b975",
    "number": "OE023208",
    "status": "Active",
    "category": "Overseas Entity",
    "country_of_origin": "SAINT LUCIA",
    "sic_code_sic_text_1": "None Supplied",
    "name": "HESPERO LTD.",
    "sic_code_sic_text_2": "",
    "sic_code_sic_text_3": "",
    "sic_code_sic_text_4": "",
    "uid": "b18fb9b7-6fcd-4353-b334-578e3b5e3415",
    "created_at": "2025-11-04 14:15:49.846752",
    "registered_address_country": "SAINT LUCIA",
    "alpha_2_country_code_registered_address_country": "LC",
    "alpha_2_country_code_country_of_origin": "LC"
  },
  {
    "payload_uid": "c74df083-3d71-42da-963e-381b9b04b975",
    "number": "OE021200",
    "status": "Active",
    "category": "Overseas Entity",
    "country_of_origin": "SAINT LUCIA",
    "sic_code_sic_text_1": "None Supplied",
    "name": "VIPOGO INTERNATIONAL LTD",
    "sic_code_sic_text_2": "",
    "sic_code_sic_text_3": "",
    "sic_code_sic_text_4": "",
    "uid": "0a4d70b5-04a5-473b-acd9-a03f427042e3",
    "created_at": "2025-11-04 14:15:49.846752",
    "registered_address_country": "SAINT LUCIA",
    "alpha_2_country_code_registered_address_country": "LC",
    "alpha_2_country_code_country_of_origin": "LC"
  },
  {
    "payload_uid": "c74df083-3d71-42da-963e-381b9b04b975",
    "number": "OE029663",
    "status": "Active",
    "category": "Overseas Entity",
    "country_of_origin": "SAINT LUCIA",
    "sic_code_sic_text_1": "None Supplied",
    "name": "HELIXO HOLDINGS LIMITED",
    "sic_code_sic_text_2": "",
    "sic_code_sic_text_3": "",
    "sic_code_sic_text_4": "",
    "uid": "49682480-eecb-4f03-a8c3-7219aeb1bca1",
    "created_at": "2025-11-04 14:15:49.846752",
    "registered_address_country": "SAINT LUCIA",
    "alpha_2_country_code_registered_address_country": "LC",
    "alpha_2_country_code_country_of_origin": "LC"
  },
  {
    "payload_uid": "c74df083-3d71-42da-963e-381b9b04b975",
    "number": "OE021286",
    "status": "Active",
    "category": "Overseas Entity",
    "country_of_origin": "SAINT LUCIA",
    "sic_code_sic_text_1": "None Supplied",
    "name": "KAROLI INVESTMENTS LTD",
    "sic_code_sic_text_2": "",
    "sic_code_sic_text_3": "",
    "sic_code_sic_text_4": "",
    "uid": "bb4c1cda-92a3-4187-81b0-f9e49e03ac9c",
    "created_at": "2025-11-04 14:15:49.846752",
    "registered_address_country": "SAINT LUCIA",
    "alpha_2_country_code_registered_address_country": "LC",
    "alpha_2_country_code_country_of_origin": "LC"
  },
  {
    "payload_uid": "c74df083-3d71-42da-963e-381b9b04b975",
    "number": "OE007197",
    "status": "Active",
    "category": "Overseas Entity",
    "country_of_origin": "SAINT LUCIA",
    "sic_code_sic_text_1": "None Supplied",
    "name": "POINCIANA LIMITED",
    "sic_code_sic_text_2": "",
    "sic_code_sic_text_3": "",
    "sic_code_sic_text_4": "",
    "uid": "f7f5007f-57f8-48fb-97d4-b75964cb620e",
    "created_at": "2025-11-04 14:15:49.846752",
    "registered_address_country": "SAINT LUCIA",
    "alpha_2_country_code_registered_address_country": "LC",
    "alpha_2_country_code_country_of_origin": "LC"
  },
  {
    "payload_uid": "c74df083-3d71-42da-963e-381b9b04b975",
    "number": "OE026990",
    "status": "Active",
    "category": "Overseas Entity",
    "country_of_origin": "SAINT LUCIA",
    "sic_code_sic_text_1": "None Supplied",
    "name": "PORCHESTER LIMITED",
    "sic_code_sic_text_2": "",
    "sic_code_sic_text_3": "",
    "sic_code_sic_text_4": "",
    "uid": "6cf75195-d25e-4d4d-91da-f9420e637a88",
    "created_at": "2025-11-04 14:15:49.846752",
    "registered_address_country": "SAINT LUCIA",
    "alpha_2_country_code_registered_address_country": "LC",
    "alpha_2_country_code_country_of_origin": "LC"
  },
  {
    "payload_uid": "c74df083-3d71-42da-963e-381b9b04b975",
    "number": "OE021875",
    "status": "Active",
    "category": "Overseas Entity",
    "country_of_origin": "SAINT LUCIA",
    "sic_code_sic_text_1": "None Supplied",
    "name": "TUNNELLIGHT LIMITED",
    "sic_code_sic_text_2": "",
    "sic_code_sic_text_3": "",
    "sic_code_sic_text_4": "",
    "uid": "b105762a-bd85-466b-86ad-7c7704772026",
    "created_at": "2025-11-04 14:15:49.846752",
    "registered_address_country": "SAINT LUCIA",
    "alpha_2_country_code_registered_address_country": "LC",
    "alpha_2_country_code_country_of_origin": "LC"
  },
  {
    "payload_uid": "c74df083-3d71-42da-963e-381b9b04b975",
    "number": "FC030186",
    "status": "Active",
    "category": "Other company type",
    "country_of_origin": "ST LUCIA",
    "sic_code_sic_text_1": "None Supplied",
    "name": "BRAMPTON (DEVON) LTD",
    "sic_code_sic_text_2": "",
    "sic_code_sic_text_3": "",
    "sic_code_sic_text_4": "",
    "uid": "03e1ea88-b77a-4326-b96c-089e0d9985d3",
    "created_at": "2025-11-04 14:15:49.846752",
    "registered_address_country": "SAINT LUCIA",
    "alpha_2_country_code_registered_address_country": "LC",
    "alpha_2_country_code_country_of_origin": "LC"
  },
  {
    "payload_uid": "c74df083-3d71-42da-963e-381b9b04b975",
    "number": "OE021240",
    "status": "Active",
    "category": "Overseas Entity",
    "country_of_origin": "SAINT LUCIA",
    "sic_code_sic_text_1": "None Supplied",
    "name": "BRANCH BUSINESS INTERNATIONAL LIMITED",
    "sic_code_sic_text_2": "",
    "sic_code_sic_text_3": "",
    "sic_code_sic_text_4": "",
    "uid": "f8d0c118-4d95-436b-a105-bf6eb9ed4664",
    "created_at": "2025-11-04 14:15:49.846752",
    "registered_address_country": "SAINT LUCIA",
    "alpha_2_country_code_registered_address_country": "LC",
    "alpha_2_country_code_country_of_origin": "LC"
  },
  {
    "payload_uid": "c74df083-3d71-42da-963e-381b9b04b975",
    "number": "OE021206",
    "status": "Active",
    "category": "Overseas Entity",
    "country_of_origin": "SAINT LUCIA",
    "sic_code_sic_text_1": "None Supplied",
    "name": "CAPELLA ASSETS LIMITED",
    "sic_code_sic_text_2": "",
    "sic_code_sic_text_3": "",
    "sic_code_sic_text_4": "",
    "uid": "caf8b9f6-9823-46d0-8363-d635a9bc4d72",
    "created_at": "2025-11-04 14:15:49.846752",
    "registered_address_country": "SAINT LUCIA",
    "alpha_2_country_code_registered_address_country": "LC",
    "alpha_2_country_code_country_of_origin": "LC"
  },
  {
    "payload_uid": "c74df083-3d71-42da-963e-381b9b04b975",
    "number": "OE024963",
    "status": "Active",
    "category": "Overseas Entity",
    "country_of_origin": "SAINT LUCIA",
    "sic_code_sic_text_1": "None Supplied",
    "name": "CLIFTON PROPERTIES (ST LUCIA) LIMITED",
    "sic_code_sic_text_2": "",
    "sic_code_sic_text_3": "",
    "sic_code_sic_text_4": "",
    "uid": "a7646b78-2dad-4593-b3f5-3aec46302021",
    "created_at": "2025-11-04 14:15:49.846752",
    "registered_address_country": "SAINT LUCIA",
    "alpha_2_country_code_registered_address_country": "LC",
    "alpha_2_country_code_country_of_origin": "LC"
  },
  {
    "payload_uid": "c74df083-3d71-42da-963e-381b9b04b975",
    "number": "OE021236",
    "status": "Active",
    "category": "Overseas Entity",
    "country_of_origin": "SAINT LUCIA",
    "sic_code_sic_text_1": "None Supplied",
    "name": "NUBAX HOLDINGS LTD",
    "sic_code_sic_text_2": "",
    "sic_code_sic_text_3": "",
    "sic_code_sic_text_4": "",
    "uid": "7cd8ff42-c771-4e2c-b09e-212455941eb9",
    "created_at": "2025-11-04 14:15:49.846752",
    "registered_address_country": "SAINT LUCIA",
    "alpha_2_country_code_registered_address_country": "LC",
    "alpha_2_country_code_country_of_origin": "LC"
  },
  {
    "payload_uid": "c74df083-3d71-42da-963e-381b9b04b975",
    "number": "OE021235",
    "status": "Active",
    "category": "Overseas Entity",
    "country_of_origin": "SAINT LUCIA",
    "sic_code_sic_text_1": "None Supplied",
    "name": "ROMNEYA CORPORATION",
    "sic_code_sic_text_2": "",
    "sic_code_sic_text_3": "",
    "sic_code_sic_text_4": "",
    "uid": "1cebf716-00ac-4798-885e-48776dcfa39b",
    "created_at": "2025-11-04 14:15:49.846752",
    "registered_address_country": "SAINT LUCIA",
    "alpha_2_country_code_registered_address_country": "LC",
    "alpha_2_country_code_country_of_origin": "LC"
  },
  {
    "payload_uid": "c74df083-3d71-42da-963e-381b9b04b975",
    "number": "OE021204",
    "status": "Active",
    "category": "Overseas Entity",
    "country_of_origin": "SAINT LUCIA",
    "sic_code_sic_text_1": "None Supplied",
    "name": "ROSSINI INVESTMENTS LIMITED",
    "sic_code_sic_text_2": "",
    "sic_code_sic_text_3": "",
    "sic_code_sic_text_4": "",
    "uid": "a5f92fb8-d177-4abb-beb2-efa32ff5cea1",
    "created_at": "2025-11-04 14:15:49.846752",
    "registered_address_country": "SAINT LUCIA",
    "alpha_2_country_code_registered_address_country": "LC",
    "alpha_2_country_code_country_of_origin": "LC"
  },
  {
    "payload_uid": "c74df083-3d71-42da-963e-381b9b04b975",
    "number": "OE015257",
    "status": "Active",
    "category": "Overseas Entity",
    "country_of_origin": "SAINT LUCIA",
    "sic_code_sic_text_1": "None Supplied",
    "name": "SUNTORY PROPERTIES LIMITED",
    "sic_code_sic_text_2": "",
    "sic_code_sic_text_3": "",
    "sic_code_sic_text_4": "",
    "uid": "565e85f9-00ac-4970-8c1c-0a98e255b6bb",
    "created_at": "2025-11-04 14:15:49.846752",
    "registered_address_country": "SAINT LUCIA",
    "alpha_2_country_code_registered_address_country": "LC",
    "alpha_2_country_code_country_of_origin": "LC"
  }
]
