[
  {
    "payload_uid": "c74df083-3d71-42da-963e-381b9b04b975",
    "number": "FC027187",
    "status": "Active",
    "category": "Other company type",
    "country_of_origin": "MONGOLIA",
    "sic_code_sic_text_1": "None Supplied",
    "name": "\"ALTAI CASHMERE\" LLC",
    "sic_code_sic_text_2": "",
    "sic_code_sic_text_3": "",
    "sic_code_sic_text_4": "",
    "uid": "0942b924-6955-4e7d-8571-42d73f19417e",
    "created_at": "2025-11-04 14:15:49.846752",
    "registered_address_country": "MONGOLIA",
    "alpha_2_country_code_registered_address_country": "MN",
    "alpha_2_country_code_country_of_origin": "MN"
  },
  {
    "payload_uid": "c74df083-3d71-42da-963e-381b9b04b975",
    "number": "FC022912",
    "status": "Active",
    "category": "Other company type",
    "country_of_origin": "MONGOLIA",
    "sic_code_sic_text_1": "None Supplied",
    "name": "DISCOVER MONGOLIA LTD.",
    "sic_code_sic_text_2": "",
    "sic_code_sic_text_3": "",
    "sic_code_sic_text_4": "",
    "uid": "1d4b27ac-6e86-4b21-8dfc-72edda1dbe2e",
    "created_at": "2025-11-04 14:15:49.846752",
    "registered_address_country": "",
    "alpha_2_country_code_registered_address_country": null,
    "alpha_2_country_code_country_of_origin": "MN"
  }
]
