[
  {
    "payload_uid": "c74df083-3d71-42da-963e-381b9b04b975",
    "number": "OE026321",
    "status": "Active",
    "category": "Overseas Entity",
    "country_of_origin": "TURKS AND CAICOS ISLANDS",
    "sic_code_sic_text_1": "None Supplied",
    "name": "2 DUNRAVEN STREET LIMITED",
    "sic_code_sic_text_2": "",
    "sic_code_sic_text_3": "",
    "sic_code_sic_text_4": "",
    "uid": "3acee15a-ef80-4c1b-a0f1-aba2c6b701c6",
    "created_at": "2025-11-04 14:15:49.846752",
    "registered_address_country": "TURKS AND CAICOS ISLANDS",
    "alpha_2_country_code_registered_address_country": "TC",
    "alpha_2_country_code_country_of_origin": "TC"
  },
  {
    "payload_uid": "c74df083-3d71-42da-963e-381b9b04b975",
    "number": "OE033257",
    "status": "Active",
    "category": "Overseas Entity",
    "country_of_origin": "TURKS AND CAICOS ISLANDS",
    "sic_code_sic_text_1": "None Supplied",
    "name": "31 GREEN STREET LIMITED",
    "sic_code_sic_text_2": "",
    "sic_code_sic_text_3": "",
    "sic_code_sic_text_4": "",
    "uid": "e61d2594-01e2-487c-8736-dabb212dbf27",
    "created_at": "2025-11-04 14:15:49.846752",
    "registered_address_country": "TURKS AND CAICOS ISLANDS",
    "alpha_2_country_code_registered_address_country": "TC",
    "alpha_2_country_code_country_of_origin": "TC"
  },
  {
    "payload_uid": "c74df083-3d71-42da-963e-381b9b04b975",
    "number": "OE022758",
    "status": "Active",
    "category": "Overseas Entity",
    "country_of_origin": "TURKS AND CAICOS ISLANDS",
    "sic_code_sic_text_1": "None Supplied",
    "name": "46-48 PARK LANE LIMITED",
    "sic_code_sic_text_2": "",
    "sic_code_sic_text_3": "",
    "sic_code_sic_text_4": "",
    "uid": "06331d57-ac62-43dd-bdd3-5ea989fed0c4",
    "created_at": "2025-11-04 14:15:49.846752",
    "registered_address_country": "TURKS AND CAICOS ISLANDS",
    "alpha_2_country_code_registered_address_country": "TC",
    "alpha_2_country_code_country_of_origin": "TC"
  },
  {
    "payload_uid": "c74df083-3d71-42da-963e-381b9b04b975",
    "number": "OE024859",
    "status": "Active",
    "category": "Overseas Entity",
    "country_of_origin": "TURKS AND CAICOS ISLANDS",
    "sic_code_sic_text_1": "None Supplied",
    "name": "ALLIANCE PROPERTY LIMITED",
    "sic_code_sic_text_2": "",
    "sic_code_sic_text_3": "",
    "sic_code_sic_text_4": "",
    "uid": "01aae3e2-5e97-4e7c-8de8-a1a8439144b2",
    "created_at": "2025-11-04 14:15:49.846752",
    "registered_address_country": "TURKS AND CAICOS ISLANDS",
    "alpha_2_country_code_registered_address_country": "TC",
    "alpha_2_country_code_country_of_origin": "TC"
  },
  {
    "payload_uid": "c74df083-3d71-42da-963e-381b9b04b975",
    "number": "OE008401",
    "status": "Active",
    "category": "Overseas Entity",
    "country_of_origin": "TURKS AND CAICOS ISLANDS",
    "sic_code_sic_text_1": "None Supplied",
    "name": "BLOOMBERG HOLDINGS LIMITED",
    "sic_code_sic_text_2": "",
    "sic_code_sic_text_3": "",
    "sic_code_sic_text_4": "",
    "uid": "591b20bc-3869-4a0f-a574-9e7a8f65fb13",
    "created_at": "2025-11-04 14:15:49.846752",
    "registered_address_country": "TURKS AND CAICOS ISLANDS",
    "alpha_2_country_code_registered_address_country": "TC",
    "alpha_2_country_code_country_of_origin": "TC"
  },
  {
    "payload_uid": "c74df083-3d71-42da-963e-381b9b04b975",
    "number": "OE033164",
    "status": "Active",
    "category": "Overseas Entity",
    "country_of_origin": "TURKS AND CAICOS ISLANDS",
    "sic_code_sic_text_1": "None Supplied",
    "name": "CD HOLDING CORP.",
    "sic_code_sic_text_2": "",
    "sic_code_sic_text_3": "",
    "sic_code_sic_text_4": "",
    "uid": "32595821-bbd3-4174-b4e2-6688690e3449",
    "created_at": "2025-11-04 14:15:49.846752",
    "registered_address_country": "TURKS AND CAICOS ISLANDS",
    "alpha_2_country_code_registered_address_country": "TC",
    "alpha_2_country_code_country_of_origin": "TC"
  },
  {
    "payload_uid": "c74df083-3d71-42da-963e-381b9b04b975",
    "number": "OE019349",
    "status": "Active",
    "category": "Overseas Entity",
    "country_of_origin": "TURKS AND CAICOS ISLANDS",
    "sic_code_sic_text_1": "None Supplied",
    "name": "CORNELIA LTD",
    "sic_code_sic_text_2": "",
    "sic_code_sic_text_3": "",
    "sic_code_sic_text_4": "",
    "uid": "d396d7f8-4fa0-40e7-be3c-a0a727043c52",
    "created_at": "2025-11-04 14:15:49.846752",
    "registered_address_country": "TURKS AND CAICOS ISLANDS",
    "alpha_2_country_code_registered_address_country": "TC",
    "alpha_2_country_code_country_of_origin": "TC"
  },
  {
    "payload_uid": "c74df083-3d71-42da-963e-381b9b04b975",
    "number": "OE021419",
    "status": "Active",
    "category": "Overseas Entity",
    "country_of_origin": "TURKS AND CAICOS ISLANDS",
    "sic_code_sic_text_1": "None Supplied",
    "name": "CRIMSON INVESTMENTS ASSETS INC",
    "sic_code_sic_text_2": "",
    "sic_code_sic_text_3": "",
    "sic_code_sic_text_4": "",
    "uid": "4f5509f0-aa9c-4136-9d5e-1252018b0d9c",
    "created_at": "2025-11-04 14:15:49.846752",
    "registered_address_country": "TURKS AND CAICOS ISLANDS",
    "alpha_2_country_code_registered_address_country": "TC",
    "alpha_2_country_code_country_of_origin": "TC"
  },
  {
    "payload_uid": "c74df083-3d71-42da-963e-381b9b04b975",
    "number": "OE007584",
    "status": "Active",
    "category": "Overseas Entity",
    "country_of_origin": "TURKS AND CAICOS ISLANDS",
    "sic_code_sic_text_1": "None Supplied",
    "name": "ESM HOLDINGS LIMITED",
    "sic_code_sic_text_2": "",
    "sic_code_sic_text_3": "",
    "sic_code_sic_text_4": "",
    "uid": "1b15e7be-1c09-4998-b087-e8d1a015585e",
    "created_at": "2025-11-04 14:15:49.846752",
    "registered_address_country": "TURKS AND CAICOS ISLANDS",
    "alpha_2_country_code_registered_address_country": "TC",
    "alpha_2_country_code_country_of_origin": "TC"
  },
  {
    "payload_uid": "c74df083-3d71-42da-963e-381b9b04b975",
    "number": "OE018609",
    "status": "Active",
    "category": "Overseas Entity",
    "country_of_origin": "TURKS AND CAICOS ISLANDS",
    "sic_code_sic_text_1": "None Supplied",
    "name": "FERNGLEN CORPORATION",
    "sic_code_sic_text_2": "",
    "sic_code_sic_text_3": "",
    "sic_code_sic_text_4": "",
    "uid": "709f62c3-d774-4612-ab0b-6a7bd46682b7",
    "created_at": "2025-11-04 14:15:49.846752",
    "registered_address_country": "TURKS AND CAICOS ISLANDS",
    "alpha_2_country_code_registered_address_country": "TC",
    "alpha_2_country_code_country_of_origin": "TC"
  },
  {
    "payload_uid": "c74df083-3d71-42da-963e-381b9b04b975",
    "number": "OE029809",
    "status": "Active",
    "category": "Overseas Entity",
    "country_of_origin": "TURKS AND CAICOS ISLANDS",
    "sic_code_sic_text_1": "None Supplied",
    "name": "GREAT TRIPPETTS ESTATE LIMITED",
    "sic_code_sic_text_2": "",
    "sic_code_sic_text_3": "",
    "sic_code_sic_text_4": "",
    "uid": "ebdb7041-2e70-4a25-b057-28e04dd6f8bc",
    "created_at": "2025-11-04 14:15:49.846752",
    "registered_address_country": "TURKS AND CAICOS ISLANDS",
    "alpha_2_country_code_registered_address_country": "TC",
    "alpha_2_country_code_country_of_origin": "TC"
  },
  {
    "payload_uid": "c74df083-3d71-42da-963e-381b9b04b975",
    "number": "OE008736",
    "status": "Active",
    "category": "Overseas Entity",
    "country_of_origin": "TURKS AND CAICOS ISLANDS",
    "sic_code_sic_text_1": "None Supplied",
    "name": "HEATHCOTE INVESTMENT CORPORATION",
    "sic_code_sic_text_2": "",
    "sic_code_sic_text_3": "",
    "sic_code_sic_text_4": "",
    "uid": "1a2ab591-58d5-480b-ae63-dc6700eb207f",
    "created_at": "2025-11-04 14:15:49.846752",
    "registered_address_country": "TURKS AND CAICOS ISLANDS",
    "alpha_2_country_code_registered_address_country": "TC",
    "alpha_2_country_code_country_of_origin": "TC"
  },
  {
    "payload_uid": "c74df083-3d71-42da-963e-381b9b04b975",
    "number": "OE015358",
    "status": "Active",
    "category": "Overseas Entity",
    "country_of_origin": "TURKS AND CAICOS ISLANDS",
    "sic_code_sic_text_1": "None Supplied",
    "name": "INNKEEPER LIMITED",
    "sic_code_sic_text_2": "",
    "sic_code_sic_text_3": "",
    "sic_code_sic_text_4": "",
    "uid": "04e2e465-acd2-42a4-ab98-598c85a7bd4e",
    "created_at": "2025-11-04 14:15:49.846752",
    "registered_address_country": "VIRGIN ISLANDS, BRITISH",
    "alpha_2_country_code_registered_address_country": "VG",
    "alpha_2_country_code_country_of_origin": "TC"
  },
  {
    "payload_uid": "c74df083-3d71-42da-963e-381b9b04b975",
    "number": "OE007356",
    "status": "Active",
    "category": "Overseas Entity",
    "country_of_origin": "TURKS AND CAICOS ISLANDS",
    "sic_code_sic_text_1": "None Supplied",
    "name": "JURE INVESTMENTS LIMITED",
    "sic_code_sic_text_2": "",
    "sic_code_sic_text_3": "",
    "sic_code_sic_text_4": "",
    "uid": "b32c6291-4e40-451f-966a-e47dac115678",
    "created_at": "2025-11-04 14:15:49.846752",
    "registered_address_country": "TURKS AND CAICOS ISLANDS",
    "alpha_2_country_code_registered_address_country": "TC",
    "alpha_2_country_code_country_of_origin": "TC"
  },
  {
    "payload_uid": "c74df083-3d71-42da-963e-381b9b04b975",
    "number": "OE015355",
    "status": "Active",
    "category": "Overseas Entity",
    "country_of_origin": "TURKS AND CAICOS ISLANDS",
    "sic_code_sic_text_1": "None Supplied",
    "name": "LA'S PLACE LIMITED",
    "sic_code_sic_text_2": "",
    "sic_code_sic_text_3": "",
    "sic_code_sic_text_4": "",
    "uid": "e5040a0a-9bf4-4987-a9eb-859244a04bb4",
    "created_at": "2025-11-04 14:15:49.846752",
    "registered_address_country": "TURKS AND CAICOS ISLANDS",
    "alpha_2_country_code_registered_address_country": "TC",
    "alpha_2_country_code_country_of_origin": "TC"
  },
  {
    "payload_uid": "c74df083-3d71-42da-963e-381b9b04b975",
    "number": "OE023375",
    "status": "Active",
    "category": "Overseas Entity",
    "country_of_origin": "TURKS AND CAICOS ISLANDS",
    "sic_code_sic_text_1": "None Supplied",
    "name": "MASHER HOLDINGS LIMITED",
    "sic_code_sic_text_2": "",
    "sic_code_sic_text_3": "",
    "sic_code_sic_text_4": "",
    "uid": "c60b613c-2283-498a-9a43-a9935e8fbc09",
    "created_at": "2025-11-04 14:15:49.846752",
    "registered_address_country": "TURKS AND CAICOS ISLANDS",
    "alpha_2_country_code_registered_address_country": "TC",
    "alpha_2_country_code_country_of_origin": "TC"
  },
  {
    "payload_uid": "c74df083-3d71-42da-963e-381b9b04b975",
    "number": "OE025984",
    "status": "Active",
    "category": "Overseas Entity",
    "country_of_origin": "TURKS AND CAICOS ISLANDS",
    "sic_code_sic_text_1": "None Supplied",
    "name": "MELVIRA INVESTMENTS LIMITED",
    "sic_code_sic_text_2": "",
    "sic_code_sic_text_3": "",
    "sic_code_sic_text_4": "",
    "uid": "5329a5b5-be8b-47f1-95e9-17ad3e2bed2e",
    "created_at": "2025-11-04 14:15:49.846752",
    "registered_address_country": "TURKS AND CAICOS ISLANDS",
    "alpha_2_country_code_registered_address_country": "TC",
    "alpha_2_country_code_country_of_origin": "TC"
  },
  {
    "payload_uid": "c74df083-3d71-42da-963e-381b9b04b975",
    "number": "OE007566",
    "status": "Active",
    "category": "Overseas Entity",
    "country_of_origin": "TURKS AND CAICOS ISLANDS",
    "sic_code_sic_text_1": "None Supplied",
    "name": "MINT HOLDINGS LIMITED",
    "sic_code_sic_text_2": "",
    "sic_code_sic_text_3": "",
    "sic_code_sic_text_4": "",
    "uid": "f507cad4-3e82-4659-b149-e520fb6fa67e",
    "created_at": "2025-11-04 14:15:49.846752",
    "registered_address_country": "TURKS AND CAICOS ISLANDS",
    "alpha_2_country_code_registered_address_country": "TC",
    "alpha_2_country_code_country_of_origin": "TC"
  },
  {
    "payload_uid": "c74df083-3d71-42da-963e-381b9b04b975",
    "number": "OE019218",
    "status": "Active",
    "category": "Overseas Entity",
    "country_of_origin": "TURKS AND CAICOS ISLANDS",
    "sic_code_sic_text_1": "None Supplied",
    "name": "MORNINGTON PROPERTIES LIMITED",
    "sic_code_sic_text_2": "",
    "sic_code_sic_text_3": "",
    "sic_code_sic_text_4": "",
    "uid": "91ca01a7-ef79-4f0b-b439-ee536e3301ef",
    "created_at": "2025-11-04 14:15:49.846752",
    "registered_address_country": "TURKS AND CAICOS ISLANDS",
    "alpha_2_country_code_registered_address_country": "TC",
    "alpha_2_country_code_country_of_origin": "TC"
  },
  {
    "payload_uid": "c74df083-3d71-42da-963e-381b9b04b975",
    "number": "OE031050",
    "status": "Active",
    "category": "Overseas Entity",
    "country_of_origin": "TURKS AND CAICOS ISLANDS",
    "sic_code_sic_text_1": "None Supplied",
    "name": "OGATE HOLDINGS LIMITED",
    "sic_code_sic_text_2": "",
    "sic_code_sic_text_3": "",
    "sic_code_sic_text_4": "",
    "uid": "4f496663-2ea7-4f29-9ab8-22e4ee972ffe",
    "created_at": "2025-11-04 14:15:49.846752",
    "registered_address_country": "TURKS AND CAICOS ISLANDS",
    "alpha_2_country_code_registered_address_country": "TC",
    "alpha_2_country_code_country_of_origin": "TC"
  },
  {
    "payload_uid": "c74df083-3d71-42da-963e-381b9b04b975",
    "number": "OE027958",
    "status": "Active",
    "category": "Overseas Entity",
    "country_of_origin": "TURKS AND CAICOS ISLANDS",
    "sic_code_sic_text_1": "None Supplied",
    "name": "PHOENIX ESTATES LIMITED",
    "sic_code_sic_text_2": "",
    "sic_code_sic_text_3": "",
    "sic_code_sic_text_4": "",
    "uid": "c665c1b2-e63c-4dca-9349-546ceab85244",
    "created_at": "2025-11-04 14:15:49.846752",
    "registered_address_country": "TURKS AND CAICOS ISLANDS",
    "alpha_2_country_code_registered_address_country": "TC",
    "alpha_2_country_code_country_of_origin": "TC"
  },
  {
    "payload_uid": "c74df083-3d71-42da-963e-381b9b04b975",
    "number": "OE024451",
    "status": "Active",
    "category": "Overseas Entity",
    "country_of_origin": "TURKS AND CAICOS ISLANDS",
    "sic_code_sic_text_1": "None Supplied",
    "name": "POMFRET HOLDINGS LIMITED",
    "sic_code_sic_text_2": "",
    "sic_code_sic_text_3": "",
    "sic_code_sic_text_4": "",
    "uid": "4899ae1c-6116-44dc-87b3-7bb22697e15f",
    "created_at": "2025-11-04 14:15:49.846752",
    "registered_address_country": "TURKS AND CAICOS ISLANDS",
    "alpha_2_country_code_registered_address_country": "TC",
    "alpha_2_country_code_country_of_origin": "TC"
  },
  {
    "payload_uid": "c74df083-3d71-42da-963e-381b9b04b975",
    "number": "OE028512",
    "status": "Active",
    "category": "Overseas Entity",
    "country_of_origin": "TURKS AND CAICOS ISLANDS",
    "sic_code_sic_text_1": "None Supplied",
    "name": "PONDEROSA HOLDINGS INC.",
    "sic_code_sic_text_2": "",
    "sic_code_sic_text_3": "",
    "sic_code_sic_text_4": "",
    "uid": "a3dfc728-1a1f-4552-be88-36557c835a6f",
    "created_at": "2025-11-04 14:15:49.846752",
    "registered_address_country": "TURKS AND CAICOS ISLANDS",
    "alpha_2_country_code_registered_address_country": "TC",
    "alpha_2_country_code_country_of_origin": "TC"
  },
  {
    "payload_uid": "c74df083-3d71-42da-963e-381b9b04b975",
    "number": "OE024434",
    "status": "Active",
    "category": "Overseas Entity",
    "country_of_origin": "TURKS AND CAICOS ISLANDS",
    "sic_code_sic_text_1": "None Supplied",
    "name": "TIMBERLAKE LIMITED",
    "sic_code_sic_text_2": "",
    "sic_code_sic_text_3": "",
    "sic_code_sic_text_4": "",
    "uid": "cc23bde5-d778-4b18-a38f-9d913215351d",
    "created_at": "2025-11-04 14:15:49.846752",
    "registered_address_country": "TURKS AND CAICOS ISLANDS",
    "alpha_2_country_code_registered_address_country": "TC",
    "alpha_2_country_code_country_of_origin": "TC"
  },
  {
    "payload_uid": "c74df083-3d71-42da-963e-381b9b04b975",
    "number": "OE029713",
    "status": "Active",
    "category": "Overseas Entity",
    "country_of_origin": "TURKS AND CAICOS ISLANDS",
    "sic_code_sic_text_1": "None Supplied",
    "name": "WALDEN INVESTMENTS LTD",
    "sic_code_sic_text_2": "",
    "sic_code_sic_text_3": "",
    "sic_code_sic_text_4": "",
    "uid": "d0ccab22-5b74-495f-8244-bbcfb9eff35c",
    "created_at": "2025-11-04 14:15:49.846752",
    "registered_address_country": "TURKS AND CAICOS ISLANDS",
    "alpha_2_country_code_registered_address_country": "TC",
    "alpha_2_country_code_country_of_origin": "TC"
  },
  {
    "payload_uid": "c74df083-3d71-42da-963e-381b9b04b975",
    "number": "FC020257",
    "status": "Active",
    "category": "Other company type",
    "country_of_origin": "TURKS & CAICOS ISLANDS",
    "sic_code_sic_text_1": "None Supplied",
    "name": "WWM ASSOCIATES LTD",
    "sic_code_sic_text_2": "",
    "sic_code_sic_text_3": "",
    "sic_code_sic_text_4": "",
    "uid": "d83f21f3-0a60-445a-8b8d-aa1ad0b47bd5",
    "created_at": "2025-11-04 14:15:49.846752",
    "registered_address_country": "TURKS AND CAICOS ISLANDS",
    "alpha_2_country_code_registered_address_country": "TC",
    "alpha_2_country_code_country_of_origin": "TC"
  },
  {
    "payload_uid": "c74df083-3d71-42da-963e-381b9b04b975",
    "number": "OE028788",
    "status": "Active",
    "category": "Overseas Entity",
    "country_of_origin": "TURKS AND CAICOS ISLANDS",
    "sic_code_sic_text_1": "None Supplied",
    "name": "ABC INTERNATIONAL CORP",
    "sic_code_sic_text_2": "",
    "sic_code_sic_text_3": "",
    "sic_code_sic_text_4": "",
    "uid": "a1e66880-925c-4bb3-87cf-7c7dd47f456c",
    "created_at": "2025-11-04 14:15:49.846752",
    "registered_address_country": "TURKS AND CAICOS ISLANDS",
    "alpha_2_country_code_registered_address_country": "TC",
    "alpha_2_country_code_country_of_origin": "TC"
  },
  {
    "payload_uid": "c74df083-3d71-42da-963e-381b9b04b975",
    "number": "OE002161",
    "status": "Active",
    "category": "Overseas Entity",
    "country_of_origin": "TURKS AND CAICOS ISLANDS",
    "sic_code_sic_text_1": "None Supplied",
    "name": "ANCHOROCK PROPERTIES LIMITED",
    "sic_code_sic_text_2": "",
    "sic_code_sic_text_3": "",
    "sic_code_sic_text_4": "",
    "uid": "04666152-3c2c-4a95-bca2-db6e50946810",
    "created_at": "2025-11-04 14:15:49.846752",
    "registered_address_country": "TURKS AND CAICOS ISLANDS",
    "alpha_2_country_code_registered_address_country": "TC",
    "alpha_2_country_code_country_of_origin": "TC"
  },
  {
    "payload_uid": "c74df083-3d71-42da-963e-381b9b04b975",
    "number": "FC026628",
    "status": "Active",
    "category": "Other company type",
    "country_of_origin": "TURKS & CAICOS ISLANDS",
    "sic_code_sic_text_1": "None Supplied",
    "name": "AXIS HOLDINGS LTD.",
    "sic_code_sic_text_2": "",
    "sic_code_sic_text_3": "",
    "sic_code_sic_text_4": "",
    "uid": "9f58ee12-8cad-429d-8617-3f85f9fddd8f",
    "created_at": "2025-11-04 14:15:49.846752",
    "registered_address_country": "TURKS AND CAICOS ISLANDS",
    "alpha_2_country_code_registered_address_country": "TC",
    "alpha_2_country_code_country_of_origin": "TC"
  },
  {
    "payload_uid": "c74df083-3d71-42da-963e-381b9b04b975",
    "number": "OE028468",
    "status": "Active",
    "category": "Overseas Entity",
    "country_of_origin": "TURKS AND CAICOS ISLANDS",
    "sic_code_sic_text_1": "None Supplied",
    "name": "BURLINGTON HOLDINGS LIMITED",
    "sic_code_sic_text_2": "",
    "sic_code_sic_text_3": "",
    "sic_code_sic_text_4": "",
    "uid": "3d3a8a3b-0cd2-4ecc-8489-3a3d58f376f8",
    "created_at": "2025-11-04 14:15:49.846752",
    "registered_address_country": "TURKS AND CAICOS ISLANDS",
    "alpha_2_country_code_registered_address_country": "TC",
    "alpha_2_country_code_country_of_origin": "TC"
  },
  {
    "payload_uid": "c74df083-3d71-42da-963e-381b9b04b975",
    "number": "OE019317",
    "status": "Active",
    "category": "Overseas Entity",
    "country_of_origin": "TURKS AND CAICOS ISLANDS",
    "sic_code_sic_text_1": "None Supplied",
    "name": "CAMELLIA LIMITED",
    "sic_code_sic_text_2": "",
    "sic_code_sic_text_3": "",
    "sic_code_sic_text_4": "",
    "uid": "054f272b-e834-405e-94be-7f591f222b02",
    "created_at": "2025-11-04 14:15:49.846752",
    "registered_address_country": "TURKS AND CAICOS ISLANDS",
    "alpha_2_country_code_registered_address_country": "TC",
    "alpha_2_country_code_country_of_origin": "TC"
  },
  {
    "payload_uid": "c74df083-3d71-42da-963e-381b9b04b975",
    "number": "OE007574",
    "status": "Active",
    "category": "Overseas Entity",
    "country_of_origin": "TURKS AND CAICOS ISLANDS",
    "sic_code_sic_text_1": "None Supplied",
    "name": "CAMEO INVESTMENTS LIMITED",
    "sic_code_sic_text_2": "",
    "sic_code_sic_text_3": "",
    "sic_code_sic_text_4": "",
    "uid": "32a8aec5-224f-4595-b451-636c82fe1bf1",
    "created_at": "2025-11-04 14:15:49.846752",
    "registered_address_country": "TURKS AND CAICOS ISLANDS",
    "alpha_2_country_code_registered_address_country": "TC",
    "alpha_2_country_code_country_of_origin": "TC"
  },
  {
    "payload_uid": "c74df083-3d71-42da-963e-381b9b04b975",
    "number": "OE004871",
    "status": "Active",
    "category": "Overseas Entity",
    "country_of_origin": "TURKS AND CAICOS ISLANDS",
    "sic_code_sic_text_1": "None Supplied",
    "name": "DANTE HOLDINGS LIMITED",
    "sic_code_sic_text_2": "",
    "sic_code_sic_text_3": "",
    "sic_code_sic_text_4": "",
    "uid": "5c4da734-adb4-4177-ac00-98fd25737291",
    "created_at": "2025-11-04 14:15:49.846752",
    "registered_address_country": "TURKS AND CAICOS ISLANDS",
    "alpha_2_country_code_registered_address_country": "TC",
    "alpha_2_country_code_country_of_origin": "TC"
  },
  {
    "payload_uid": "c74df083-3d71-42da-963e-381b9b04b975",
    "number": "OE018537",
    "status": "Active",
    "category": "Overseas Entity",
    "country_of_origin": "TURKS AND CAICOS ISLANDS",
    "sic_code_sic_text_1": "None Supplied",
    "name": "DORSET HOLDINGS LTD",
    "sic_code_sic_text_2": "",
    "sic_code_sic_text_3": "",
    "sic_code_sic_text_4": "",
    "uid": "9ceb0597-9f42-4281-a1b2-af5298da54ef",
    "created_at": "2025-11-04 14:15:49.846752",
    "registered_address_country": "TURKS AND CAICOS ISLANDS",
    "alpha_2_country_code_registered_address_country": "TC",
    "alpha_2_country_code_country_of_origin": "TC"
  },
  {
    "payload_uid": "c74df083-3d71-42da-963e-381b9b04b975",
    "number": "OE016969",
    "status": "Active",
    "category": "Overseas Entity",
    "country_of_origin": "TURKS AND CAICOS ISLANDS",
    "sic_code_sic_text_1": "None Supplied",
    "name": "EATON CORPORATION LIMITED",
    "sic_code_sic_text_2": "",
    "sic_code_sic_text_3": "",
    "sic_code_sic_text_4": "",
    "uid": "86e327ab-2da7-4845-a1c7-fcd054f3dff6",
    "created_at": "2025-11-04 14:15:49.846752",
    "registered_address_country": "TURKS AND CAICOS ISLANDS",
    "alpha_2_country_code_registered_address_country": "TC",
    "alpha_2_country_code_country_of_origin": "TC"
  },
  {
    "payload_uid": "c74df083-3d71-42da-963e-381b9b04b975",
    "number": "FC033673",
    "status": "Active",
    "category": "Other company type",
    "country_of_origin": "TURKS & CAICOS ISLANDS",
    "sic_code_sic_text_1": "None Supplied",
    "name": "FAEZ LIMITED",
    "sic_code_sic_text_2": "",
    "sic_code_sic_text_3": "",
    "sic_code_sic_text_4": "",
    "uid": "0a5a55fa-105c-418e-981c-c1201f065196",
    "created_at": "2025-11-04 14:15:49.846752",
    "registered_address_country": "BRITISH WEST INDIES",
    "alpha_2_country_code_registered_address_country": null,
    "alpha_2_country_code_country_of_origin": "TC"
  },
  {
    "payload_uid": "c74df083-3d71-42da-963e-381b9b04b975",
    "number": "OE028496",
    "status": "Active",
    "category": "Overseas Entity",
    "country_of_origin": "TURKS AND CAICOS ISLANDS",
    "sic_code_sic_text_1": "None Supplied",
    "name": "FAEZ LIMITED",
    "sic_code_sic_text_2": "",
    "sic_code_sic_text_3": "",
    "sic_code_sic_text_4": "",
    "uid": "b3f69bea-c33e-4bf5-bf07-12245b97f8ab",
    "created_at": "2025-11-04 14:15:49.846752",
    "registered_address_country": "TURKS AND CAICOS ISLANDS",
    "alpha_2_country_code_registered_address_country": "TC",
    "alpha_2_country_code_country_of_origin": "TC"
  },
  {
    "payload_uid": "c74df083-3d71-42da-963e-381b9b04b975",
    "number": "OE010616",
    "status": "Active",
    "category": "Overseas Entity",
    "country_of_origin": "TURKS AND CAICOS ISLANDS",
    "sic_code_sic_text_1": "None Supplied",
    "name": "FORTON INVESTMENTS LIMITED",
    "sic_code_sic_text_2": "",
    "sic_code_sic_text_3": "",
    "sic_code_sic_text_4": "",
    "uid": "cc3a5bee-bb1d-4bcf-bb9d-d9c65ad4c596",
    "created_at": "2025-11-04 14:15:49.846752",
    "registered_address_country": "TURKS AND CAICOS ISLANDS",
    "alpha_2_country_code_registered_address_country": "TC",
    "alpha_2_country_code_country_of_origin": "TC"
  },
  {
    "payload_uid": "c74df083-3d71-42da-963e-381b9b04b975",
    "number": "OE008699",
    "status": "Active",
    "category": "Overseas Entity",
    "country_of_origin": "TURKS AND CAICOS ISLANDS",
    "sic_code_sic_text_1": "None Supplied",
    "name": "GLENHEATHE INVESTMENTS LIMITED",
    "sic_code_sic_text_2": "",
    "sic_code_sic_text_3": "",
    "sic_code_sic_text_4": "",
    "uid": "42fd1804-9479-4079-955d-ed892d18f9a6",
    "created_at": "2025-11-04 14:15:49.846752",
    "registered_address_country": "TURKS AND CAICOS ISLANDS",
    "alpha_2_country_code_registered_address_country": "TC",
    "alpha_2_country_code_country_of_origin": "TC"
  },
  {
    "payload_uid": "c74df083-3d71-42da-963e-381b9b04b975",
    "number": "FC016099",
    "status": "Active",
    "category": "Other company type",
    "country_of_origin": "TURKS & CAICOS ISLANDS",
    "sic_code_sic_text_1": "None Supplied",
    "name": "HOTSPUR ENTERPRISES LIMITED",
    "sic_code_sic_text_2": "",
    "sic_code_sic_text_3": "",
    "sic_code_sic_text_4": "",
    "uid": "e09d57e1-0aed-43c6-9b26-b732240532c8",
    "created_at": "2025-11-04 14:15:49.846752",
    "registered_address_country": "TURKS AND CAICOS ISLANDS",
    "alpha_2_country_code_registered_address_country": "TC",
    "alpha_2_country_code_country_of_origin": "TC"
  },
  {
    "payload_uid": "c74df083-3d71-42da-963e-381b9b04b975",
    "number": "OE025862",
    "status": "Active",
    "category": "Overseas Entity",
    "country_of_origin": "TURKS AND CAICOS ISLANDS",
    "sic_code_sic_text_1": "None Supplied",
    "name": "JAMARM HOLDINGS LIMITED",
    "sic_code_sic_text_2": "",
    "sic_code_sic_text_3": "",
    "sic_code_sic_text_4": "",
    "uid": "b7b60ad2-bcdf-4075-a693-041b0434a030",
    "created_at": "2025-11-04 14:15:49.846752",
    "registered_address_country": "TURKS AND CAICOS ISLANDS",
    "alpha_2_country_code_registered_address_country": "TC",
    "alpha_2_country_code_country_of_origin": "TC"
  },
  {
    "payload_uid": "c74df083-3d71-42da-963e-381b9b04b975",
    "number": "OE020012",
    "status": "Active",
    "category": "Overseas Entity",
    "country_of_origin": "TURKS AND CAICOS ISLANDS",
    "sic_code_sic_text_1": "None Supplied",
    "name": "LACOSTE INVESTMENTS LTD",
    "sic_code_sic_text_2": "",
    "sic_code_sic_text_3": "",
    "sic_code_sic_text_4": "",
    "uid": "818d7e5e-6115-464c-abe5-53c7b31753b6",
    "created_at": "2025-11-04 14:15:49.846752",
    "registered_address_country": "JERSEY",
    "alpha_2_country_code_registered_address_country": "JE",
    "alpha_2_country_code_country_of_origin": "TC"
  },
  {
    "payload_uid": "c74df083-3d71-42da-963e-381b9b04b975",
    "number": "OE031261",
    "status": "Active",
    "category": "Overseas Entity",
    "country_of_origin": "TURKS AND CAICOS ISLANDS",
    "sic_code_sic_text_1": "None Supplied",
    "name": "LENNO CORPORATION",
    "sic_code_sic_text_2": "",
    "sic_code_sic_text_3": "",
    "sic_code_sic_text_4": "",
    "uid": "cd75424b-80d1-4cfa-97fe-37bbc55d2546",
    "created_at": "2025-11-04 14:15:49.846752",
    "registered_address_country": "TURKS AND CAICOS ISLANDS",
    "alpha_2_country_code_registered_address_country": "TC",
    "alpha_2_country_code_country_of_origin": "TC"
  },
  {
    "payload_uid": "c74df083-3d71-42da-963e-381b9b04b975",
    "number": "OE026319",
    "status": "Active",
    "category": "Overseas Entity",
    "country_of_origin": "TURKS AND CAICOS ISLANDS",
    "sic_code_sic_text_1": "None Supplied",
    "name": "LINGWOOD PROPERTIES LIMITED",
    "sic_code_sic_text_2": "",
    "sic_code_sic_text_3": "",
    "sic_code_sic_text_4": "",
    "uid": "46648b8c-fac1-4a75-a421-fbe88e30703b",
    "created_at": "2025-11-04 14:15:49.846752",
    "registered_address_country": "TURKS AND CAICOS ISLANDS",
    "alpha_2_country_code_registered_address_country": "TC",
    "alpha_2_country_code_country_of_origin": "TC"
  },
  {
    "payload_uid": "c74df083-3d71-42da-963e-381b9b04b975",
    "number": "OE007609",
    "status": "Active",
    "category": "Overseas Entity",
    "country_of_origin": "TURKS AND CAICOS ISLANDS",
    "sic_code_sic_text_1": "None Supplied",
    "name": "MERIDIAN GROUP LIMITED",
    "sic_code_sic_text_2": "",
    "sic_code_sic_text_3": "",
    "sic_code_sic_text_4": "",
    "uid": "12ecc3ca-5121-4f37-baf5-7ae9c54bdf05",
    "created_at": "2025-11-04 14:15:49.846752",
    "registered_address_country": "TURKS AND CAICOS ISLANDS",
    "alpha_2_country_code_registered_address_country": "TC",
    "alpha_2_country_code_country_of_origin": "TC"
  },
  {
    "payload_uid": "c74df083-3d71-42da-963e-381b9b04b975",
    "number": "OE010394",
    "status": "Active",
    "category": "Overseas Entity",
    "country_of_origin": "TURKS AND CAICOS ISLANDS",
    "sic_code_sic_text_1": "None Supplied",
    "name": "NEVIS INVESTMENTS LIMITED",
    "sic_code_sic_text_2": "",
    "sic_code_sic_text_3": "",
    "sic_code_sic_text_4": "",
    "uid": "d0d6f18e-6838-4bac-af2e-4a8226d63ab1",
    "created_at": "2025-11-04 14:15:49.846752",
    "registered_address_country": "TURKS AND CAICOS ISLANDS",
    "alpha_2_country_code_registered_address_country": "TC",
    "alpha_2_country_code_country_of_origin": "TC"
  },
  {
    "payload_uid": "c74df083-3d71-42da-963e-381b9b04b975",
    "number": "OE026287",
    "status": "Active",
    "category": "Overseas Entity",
    "country_of_origin": "TURKS AND CAICOS ISLANDS",
    "sic_code_sic_text_1": "None Supplied",
    "name": "NIMBA PROPERTIES LIMITED",
    "sic_code_sic_text_2": "",
    "sic_code_sic_text_3": "",
    "sic_code_sic_text_4": "",
    "uid": "e621db78-e952-4880-9c2b-5e3cda1a2f6f",
    "created_at": "2025-11-04 14:15:49.846752",
    "registered_address_country": "TURKS AND CAICOS ISLANDS",
    "alpha_2_country_code_registered_address_country": "TC",
    "alpha_2_country_code_country_of_origin": "TC"
  },
  {
    "payload_uid": "c74df083-3d71-42da-963e-381b9b04b975",
    "number": "FC026401",
    "status": "Active",
    "category": "Other company type",
    "country_of_origin": "TURKS & CAICOS ISLANDS",
    "sic_code_sic_text_1": "None Supplied",
    "name": "PALLADINO HOLDINGS LIMITED",
    "sic_code_sic_text_2": "",
    "sic_code_sic_text_3": "",
    "sic_code_sic_text_4": "",
    "uid": "5928d1ea-41b7-4afd-b8b1-095d9ca8a601",
    "created_at": "2025-11-04 14:15:49.846752",
    "registered_address_country": "",
    "alpha_2_country_code_registered_address_country": null,
    "alpha_2_country_code_country_of_origin": "TC"
  },
  {
    "payload_uid": "c74df083-3d71-42da-963e-381b9b04b975",
    "number": "OE026286",
    "status": "Active",
    "category": "Overseas Entity",
    "country_of_origin": "TURKS AND CAICOS ISLANDS",
    "sic_code_sic_text_1": "None Supplied",
    "name": "PENTHOUSE D LIMITED",
    "sic_code_sic_text_2": "",
    "sic_code_sic_text_3": "",
    "sic_code_sic_text_4": "",
    "uid": "30ae98bc-f68b-4b4f-9291-b8608b399343",
    "created_at": "2025-11-04 14:15:49.846752",
    "registered_address_country": "TURKS AND CAICOS ISLANDS",
    "alpha_2_country_code_registered_address_country": "TC",
    "alpha_2_country_code_country_of_origin": "TC"
  },
  {
    "payload_uid": "c74df083-3d71-42da-963e-381b9b04b975",
    "number": "OE012348",
    "status": "Active",
    "category": "Overseas Entity",
    "country_of_origin": "TURKS AND CAICOS ISLANDS",
    "sic_code_sic_text_1": "None Supplied",
    "name": "PESO INVESTMENTS LIMITED",
    "sic_code_sic_text_2": "",
    "sic_code_sic_text_3": "",
    "sic_code_sic_text_4": "",
    "uid": "35142ffc-ccc8-4ffc-923c-756d490261b5",
    "created_at": "2025-11-04 14:15:49.846752",
    "registered_address_country": "TURKS AND CAICOS ISLANDS",
    "alpha_2_country_code_registered_address_country": "TC",
    "alpha_2_country_code_country_of_origin": "TC"
  },
  {
    "payload_uid": "c74df083-3d71-42da-963e-381b9b04b975",
    "number": "OE019852",
    "status": "Active",
    "category": "Overseas Entity",
    "country_of_origin": "TURKS AND CAICOS ISLANDS",
    "sic_code_sic_text_1": "None Supplied",
    "name": "PROSPECT TECHNOLOGY LTD",
    "sic_code_sic_text_2": "",
    "sic_code_sic_text_3": "",
    "sic_code_sic_text_4": "",
    "uid": "de4e323e-d6ee-4bef-a0bd-a458a78d63d9",
    "created_at": "2025-11-04 14:15:49.846752",
    "registered_address_country": "TURKS AND CAICOS ISLANDS",
    "alpha_2_country_code_registered_address_country": "TC",
    "alpha_2_country_code_country_of_origin": "TC"
  },
  {
    "payload_uid": "c74df083-3d71-42da-963e-381b9b04b975",
    "number": "OE019432",
    "status": "Active",
    "category": "Overseas Entity",
    "country_of_origin": "TURKS AND CAICOS ISLANDS",
    "sic_code_sic_text_1": "None Supplied",
    "name": "RESOLUTION HOLDINGS LIMITED",
    "sic_code_sic_text_2": "",
    "sic_code_sic_text_3": "",
    "sic_code_sic_text_4": "",
    "uid": "a1e0e3c3-973c-403e-b4cd-d65bc1028914",
    "created_at": "2025-11-04 14:15:49.846752",
    "registered_address_country": "TURKS AND CAICOS ISLANDS",
    "alpha_2_country_code_registered_address_country": "TC",
    "alpha_2_country_code_country_of_origin": "TC"
  },
  {
    "payload_uid": "c74df083-3d71-42da-963e-381b9b04b975",
    "number": "OE016222",
    "status": "Active",
    "category": "Overseas Entity",
    "country_of_origin": "TURKS AND CAICOS ISLANDS",
    "sic_code_sic_text_1": "None Supplied",
    "name": "RISETALL LIMITED",
    "sic_code_sic_text_2": "",
    "sic_code_sic_text_3": "",
    "sic_code_sic_text_4": "",
    "uid": "6a355290-9384-4663-9027-9384f2d8de8c",
    "created_at": "2025-11-04 14:15:49.846752",
    "registered_address_country": "",
    "alpha_2_country_code_registered_address_country": null,
    "alpha_2_country_code_country_of_origin": "TC"
  },
  {
    "payload_uid": "c74df083-3d71-42da-963e-381b9b04b975",
    "number": "OE028469",
    "status": "Active",
    "category": "Overseas Entity",
    "country_of_origin": "TURKS AND CAICOS ISLANDS",
    "sic_code_sic_text_1": "None Supplied",
    "name": "ROWLAND DEANE LIMITED",
    "sic_code_sic_text_2": "",
    "sic_code_sic_text_3": "",
    "sic_code_sic_text_4": "",
    "uid": "2829bd10-48fa-41b2-8689-73cce8c8b670",
    "created_at": "2025-11-04 14:15:49.846752",
    "registered_address_country": "TURKS AND CAICOS ISLANDS",
    "alpha_2_country_code_registered_address_country": "TC",
    "alpha_2_country_code_country_of_origin": "TC"
  },
  {
    "payload_uid": "c74df083-3d71-42da-963e-381b9b04b975",
    "number": "OE020675",
    "status": "Active",
    "category": "Overseas Entity",
    "country_of_origin": "TURKS AND CAICOS ISLANDS",
    "sic_code_sic_text_1": "None Supplied",
    "name": "SANTREX HOLDINGS LIMITED",
    "sic_code_sic_text_2": "",
    "sic_code_sic_text_3": "",
    "sic_code_sic_text_4": "",
    "uid": "5603914a-4b11-4487-b85f-457d9cb64253",
    "created_at": "2025-11-04 14:15:49.846752",
    "registered_address_country": "TURKS AND CAICOS ISLANDS",
    "alpha_2_country_code_registered_address_country": "TC",
    "alpha_2_country_code_country_of_origin": "TC"
  },
  {
    "payload_uid": "c74df083-3d71-42da-963e-381b9b04b975",
    "number": "OE029835",
    "status": "Active",
    "category": "Overseas Entity",
    "country_of_origin": "TURKS AND CAICOS ISLANDS",
    "sic_code_sic_text_1": "None Supplied",
    "name": "SCOTTISH HERITAGE ASSOCIATION LTD",
    "sic_code_sic_text_2": "",
    "sic_code_sic_text_3": "",
    "sic_code_sic_text_4": "",
    "uid": "051e7fc2-7aca-4f8f-8d3a-2da0a5c5091e",
    "created_at": "2025-11-04 14:15:49.846752",
    "registered_address_country": "TURKS AND CAICOS ISLANDS",
    "alpha_2_country_code_registered_address_country": "TC",
    "alpha_2_country_code_country_of_origin": "TC"
  },
  {
    "payload_uid": "c74df083-3d71-42da-963e-381b9b04b975",
    "number": "OE011089",
    "status": "Active",
    "category": "Overseas Entity",
    "country_of_origin": "TURKS AND CAICOS ISLANDS",
    "sic_code_sic_text_1": "None Supplied",
    "name": "SHARP HOLDINGS LTD",
    "sic_code_sic_text_2": "",
    "sic_code_sic_text_3": "",
    "sic_code_sic_text_4": "",
    "uid": "e313a00c-11e4-4278-84e0-8683f8811a7c",
    "created_at": "2025-11-04 14:15:49.846752",
    "registered_address_country": "TURKS AND CAICOS ISLANDS",
    "alpha_2_country_code_registered_address_country": "TC",
    "alpha_2_country_code_country_of_origin": "TC"
  },
  {
    "payload_uid": "c74df083-3d71-42da-963e-381b9b04b975",
    "number": "OE020593",
    "status": "Active",
    "category": "Overseas Entity",
    "country_of_origin": "TURKS AND CAICOS ISLANDS",
    "sic_code_sic_text_1": "None Supplied",
    "name": "SHAWDALE LIMITED",
    "sic_code_sic_text_2": "",
    "sic_code_sic_text_3": "",
    "sic_code_sic_text_4": "",
    "uid": "357b0775-8595-42d3-8e84-cd43ecbee54e",
    "created_at": "2025-11-04 14:15:49.846752",
    "registered_address_country": "TURKS AND CAICOS ISLANDS",
    "alpha_2_country_code_registered_address_country": "TC",
    "alpha_2_country_code_country_of_origin": "TC"
  },
  {
    "payload_uid": "c74df083-3d71-42da-963e-381b9b04b975",
    "number": "OE030122",
    "status": "Active",
    "category": "Overseas Entity",
    "country_of_origin": "TURKS AND CAICOS ISLANDS",
    "sic_code_sic_text_1": "None Supplied",
    "name": "TEMEAD MANAGEMENT LIMITED",
    "sic_code_sic_text_2": "",
    "sic_code_sic_text_3": "",
    "sic_code_sic_text_4": "",
    "uid": "5957b6fa-8d99-423c-a648-fb8c215530b2",
    "created_at": "2025-11-04 14:15:49.846752",
    "registered_address_country": "TURKS AND CAICOS ISLANDS",
    "alpha_2_country_code_registered_address_country": "TC",
    "alpha_2_country_code_country_of_origin": "TC"
  },
  {
    "payload_uid": "c74df083-3d71-42da-963e-381b9b04b975",
    "number": "OE007570",
    "status": "Active",
    "category": "Overseas Entity",
    "country_of_origin": "TURKS AND CAICOS ISLANDS",
    "sic_code_sic_text_1": "None Supplied",
    "name": "VISTA GROUP LTD",
    "sic_code_sic_text_2": "",
    "sic_code_sic_text_3": "",
    "sic_code_sic_text_4": "",
    "uid": "c39ba778-d58c-4ce8-a95b-ee3f6475d24f",
    "created_at": "2025-11-04 14:15:49.846752",
    "registered_address_country": "TURKS AND CAICOS ISLANDS",
    "alpha_2_country_code_registered_address_country": "TC",
    "alpha_2_country_code_country_of_origin": "TC"
  },
  {
    "payload_uid": "c74df083-3d71-42da-963e-381b9b04b975",
    "number": "OE026324",
    "status": "Active",
    "category": "Overseas Entity",
    "country_of_origin": "TURKS AND CAICOS ISLANDS",
    "sic_code_sic_text_1": "None Supplied",
    "name": "WELLINGTON PROPERTIES LIMITED",
    "sic_code_sic_text_2": "",
    "sic_code_sic_text_3": "",
    "sic_code_sic_text_4": "",
    "uid": "de204538-05e0-432b-81f5-b3849f7682f9",
    "created_at": "2025-11-04 14:15:49.846752",
    "registered_address_country": "TURKS AND CAICOS ISLANDS",
    "alpha_2_country_code_registered_address_country": "TC",
    "alpha_2_country_code_country_of_origin": "TC"
  },
  {
    "payload_uid": "c74df083-3d71-42da-963e-381b9b04b975",
    "number": "OE012351",
    "status": "Active",
    "category": "Overseas Entity",
    "country_of_origin": "TURKS AND CAICOS ISLANDS",
    "sic_code_sic_text_1": "None Supplied",
    "name": "ZAP HOLDINGS LIMITED",
    "sic_code_sic_text_2": "",
    "sic_code_sic_text_3": "",
    "sic_code_sic_text_4": "",
    "uid": "00054069-55a4-419f-bbb5-7ba5e83c65af",
    "created_at": "2025-11-04 14:15:49.846752",
    "registered_address_country": "TURKS AND CAICOS ISLANDS",
    "alpha_2_country_code_registered_address_country": "TC",
    "alpha_2_country_code_country_of_origin": "TC"
  },
  {
    "payload_uid": "c74df083-3d71-42da-963e-381b9b04b975",
    "number": "OE007322",
    "status": "Active",
    "category": "Overseas Entity",
    "country_of_origin": "TURKS AND CAICOS ISLANDS",
    "sic_code_sic_text_1": "None Supplied",
    "name": "ACCESS HOLDINGS LIMITED",
    "sic_code_sic_text_2": "",
    "sic_code_sic_text_3": "",
    "sic_code_sic_text_4": "",
    "uid": "ca6e5f8e-db25-4e1d-a5e1-e948b5c75f94",
    "created_at": "2025-11-04 14:15:49.846752",
    "registered_address_country": "TURKS AND CAICOS ISLANDS",
    "alpha_2_country_code_registered_address_country": "TC",
    "alpha_2_country_code_country_of_origin": "TC"
  },
  {
    "payload_uid": "c74df083-3d71-42da-963e-381b9b04b975",
    "number": "OE026504",
    "status": "Active",
    "category": "Overseas Entity",
    "country_of_origin": "TURKS AND CAICOS ISLANDS",
    "sic_code_sic_text_1": "None Supplied",
    "name": "AEGIS SERVICES LIMITED",
    "sic_code_sic_text_2": "",
    "sic_code_sic_text_3": "",
    "sic_code_sic_text_4": "",
    "uid": "f3513912-e23c-49ae-9749-f83e26f3ffe2",
    "created_at": "2025-11-04 14:15:49.846752",
    "registered_address_country": "TURKS AND CAICOS ISLANDS",
    "alpha_2_country_code_registered_address_country": "TC",
    "alpha_2_country_code_country_of_origin": "TC"
  },
  {
    "payload_uid": "c74df083-3d71-42da-963e-381b9b04b975",
    "number": "OE029244",
    "status": "Active",
    "category": "Overseas Entity",
    "country_of_origin": "TURKS AND CAICOS ISLANDS",
    "sic_code_sic_text_1": "None Supplied",
    "name": "B.V.S.I. INVESTMENT HOLDINGS LTD.",
    "sic_code_sic_text_2": "",
    "sic_code_sic_text_3": "",
    "sic_code_sic_text_4": "",
    "uid": "4ec645b1-5d9c-4205-aad0-86e84f40984f",
    "created_at": "2025-11-04 14:15:49.846752",
    "registered_address_country": "TURKS AND CAICOS ISLANDS",
    "alpha_2_country_code_registered_address_country": "TC",
    "alpha_2_country_code_country_of_origin": "TC"
  },
  {
    "payload_uid": "c74df083-3d71-42da-963e-381b9b04b975",
    "number": "OE026322",
    "status": "Active",
    "category": "Overseas Entity",
    "country_of_origin": "TURKS AND CAICOS ISLANDS",
    "sic_code_sic_text_1": "None Supplied",
    "name": "BARRINGTON PROPERTIES LIMITED",
    "sic_code_sic_text_2": "",
    "sic_code_sic_text_3": "",
    "sic_code_sic_text_4": "",
    "uid": "71f63794-eb6f-4f05-8d41-b4c7aa47a30e",
    "created_at": "2025-11-04 14:15:49.846752",
    "registered_address_country": "TURKS AND CAICOS ISLANDS",
    "alpha_2_country_code_registered_address_country": "TC",
    "alpha_2_country_code_country_of_origin": "TC"
  },
  {
    "payload_uid": "c74df083-3d71-42da-963e-381b9b04b975",
    "number": "OE027619",
    "status": "Active",
    "category": "Overseas Entity",
    "country_of_origin": "TURKS AND CAICOS ISLANDS",
    "sic_code_sic_text_1": "None Supplied",
    "name": "BEAUCHAMP HOLDINGS LIMITED",
    "sic_code_sic_text_2": "",
    "sic_code_sic_text_3": "",
    "sic_code_sic_text_4": "",
    "uid": "6c1b1476-0dbc-4796-bcbf-7d882b94110d",
    "created_at": "2025-11-04 14:15:49.846752",
    "registered_address_country": "TURKS AND CAICOS ISLANDS",
    "alpha_2_country_code_registered_address_country": "TC",
    "alpha_2_country_code_country_of_origin": "TC"
  },
  {
    "payload_uid": "c74df083-3d71-42da-963e-381b9b04b975",
    "number": "OE003380",
    "status": "Active",
    "category": "Overseas Entity",
    "country_of_origin": "TURKS AND CAICOS ISLANDS",
    "sic_code_sic_text_1": "None Supplied",
    "name": "BELMONT INVESTMENTS LIMITED",
    "sic_code_sic_text_2": "",
    "sic_code_sic_text_3": "",
    "sic_code_sic_text_4": "",
    "uid": "ea2148b7-76c2-4727-b4a2-7693221c9b56",
    "created_at": "2025-11-04 14:15:49.846752",
    "registered_address_country": "TURKS AND CAICOS ISLANDS",
    "alpha_2_country_code_registered_address_country": "TC",
    "alpha_2_country_code_country_of_origin": "TC"
  },
  {
    "payload_uid": "c74df083-3d71-42da-963e-381b9b04b975",
    "number": "OE024177",
    "status": "Active",
    "category": "Overseas Entity",
    "country_of_origin": "ISLE OF MAN",
    "sic_code_sic_text_1": "None Supplied",
    "name": "BRONMOOR LIMITED",
    "sic_code_sic_text_2": "",
    "sic_code_sic_text_3": "",
    "sic_code_sic_text_4": "",
    "uid": "7b55629a-c354-498d-978b-e7e6bb61ba7e",
    "created_at": "2025-11-04 14:15:49.846752",
    "registered_address_country": "TURKS AND CAICOS ISLANDS",
    "alpha_2_country_code_registered_address_country": "TC",
    "alpha_2_country_code_country_of_origin": "IM"
  },
  {
    "payload_uid": "c74df083-3d71-42da-963e-381b9b04b975",
    "number": "OE019883",
    "status": "Active",
    "category": "Overseas Entity",
    "country_of_origin": "TURKS AND CAICOS ISLANDS",
    "sic_code_sic_text_1": "None Supplied",
    "name": "CHUFFIE INVESTMENTS LIMITED",
    "sic_code_sic_text_2": "",
    "sic_code_sic_text_3": "",
    "sic_code_sic_text_4": "",
    "uid": "95bf6493-8750-44b2-b005-48bc007f1ab2",
    "created_at": "2025-11-04 14:15:49.846752",
    "registered_address_country": "TURKS AND CAICOS ISLANDS",
    "alpha_2_country_code_registered_address_country": "TC",
    "alpha_2_country_code_country_of_origin": "TC"
  },
  {
    "payload_uid": "c74df083-3d71-42da-963e-381b9b04b975",
    "number": "OE012550",
    "status": "Active",
    "category": "Overseas Entity",
    "country_of_origin": "TURKS AND CAICOS ISLANDS",
    "sic_code_sic_text_1": "None Supplied",
    "name": "COLLEN INVESTMENTS LIMITED",
    "sic_code_sic_text_2": "",
    "sic_code_sic_text_3": "",
    "sic_code_sic_text_4": "",
    "uid": "db3c6574-e90c-4607-967c-9721a9115685",
    "created_at": "2025-11-04 14:15:49.846752",
    "registered_address_country": "TURKS AND CAICOS ISLANDS",
    "alpha_2_country_code_registered_address_country": "TC",
    "alpha_2_country_code_country_of_origin": "TC"
  },
  {
    "payload_uid": "c74df083-3d71-42da-963e-381b9b04b975",
    "number": "OE029820",
    "status": "Active",
    "category": "Overseas Entity",
    "country_of_origin": "TURKS AND CAICOS ISLANDS",
    "sic_code_sic_text_1": "None Supplied",
    "name": "COLLISTO INVESTMENTS LIMITED",
    "sic_code_sic_text_2": "",
    "sic_code_sic_text_3": "",
    "sic_code_sic_text_4": "",
    "uid": "5a6b8674-0de1-4f8b-baaa-aa3ec3ac2ead",
    "created_at": "2025-11-04 14:15:49.846752",
    "registered_address_country": "TURKS AND CAICOS ISLANDS",
    "alpha_2_country_code_registered_address_country": "TC",
    "alpha_2_country_code_country_of_origin": "TC"
  },
  {
    "payload_uid": "c74df083-3d71-42da-963e-381b9b04b975",
    "number": "OE026308",
    "status": "Active",
    "category": "Overseas Entity",
    "country_of_origin": "TURKS AND CAICOS ISLANDS",
    "sic_code_sic_text_1": "None Supplied",
    "name": "DELAURIAN LTD.",
    "sic_code_sic_text_2": "",
    "sic_code_sic_text_3": "",
    "sic_code_sic_text_4": "",
    "uid": "32b57feb-0482-44d1-a791-60def73f270d",
    "created_at": "2025-11-04 14:15:49.846752",
    "registered_address_country": "TURKS AND CAICOS ISLANDS",
    "alpha_2_country_code_registered_address_country": "TC",
    "alpha_2_country_code_country_of_origin": "TC"
  },
  {
    "payload_uid": "c74df083-3d71-42da-963e-381b9b04b975",
    "number": "OE033992",
    "status": "Active",
    "category": "Overseas Entity",
    "country_of_origin": "TURKS AND CAICOS ISLANDS",
    "sic_code_sic_text_1": "None Supplied",
    "name": "DRAKE PROPERTIES LIMITED",
    "sic_code_sic_text_2": "",
    "sic_code_sic_text_3": "",
    "sic_code_sic_text_4": "",
    "uid": "ac34c195-cb7e-496e-ad35-475e506852a4",
    "created_at": "2025-11-04 14:15:49.846752",
    "registered_address_country": "TURKS AND CAICOS ISLANDS",
    "alpha_2_country_code_registered_address_country": "TC",
    "alpha_2_country_code_country_of_origin": "TC"
  },
  {
    "payload_uid": "c74df083-3d71-42da-963e-381b9b04b975",
    "number": "FC017153",
    "status": "Active",
    "category": "Other company type",
    "country_of_origin": "TURKS & CAICOS ISLANDS",
    "sic_code_sic_text_1": "None Supplied",
    "name": "ECHO INVESTMENTS LIMITED",
    "sic_code_sic_text_2": "",
    "sic_code_sic_text_3": "",
    "sic_code_sic_text_4": "",
    "uid": "e158775a-e458-479b-bb71-e6a5ba7480a7",
    "created_at": "2025-11-04 14:15:49.846752",
    "registered_address_country": "",
    "alpha_2_country_code_registered_address_country": null,
    "alpha_2_country_code_country_of_origin": "TC"
  },
  {
    "payload_uid": "c74df083-3d71-42da-963e-381b9b04b975",
    "number": "OE003641",
    "status": "Active",
    "category": "Overseas Entity",
    "country_of_origin": "TURKS AND CAICOS ISLANDS",
    "sic_code_sic_text_1": "None Supplied",
    "name": "FOLKSAIL LIMITED",
    "sic_code_sic_text_2": "",
    "sic_code_sic_text_3": "",
    "sic_code_sic_text_4": "",
    "uid": "4be8c722-a0b5-4c91-b603-01e0616525af",
    "created_at": "2025-11-04 14:15:49.846752",
    "registered_address_country": "TURKS AND CAICOS ISLANDS",
    "alpha_2_country_code_registered_address_country": "TC",
    "alpha_2_country_code_country_of_origin": "TC"
  },
  {
    "payload_uid": "c74df083-3d71-42da-963e-381b9b04b975",
    "number": "OE026112",
    "status": "Active",
    "category": "Overseas Entity",
    "country_of_origin": "TURKS AND CAICOS ISLANDS",
    "sic_code_sic_text_1": "None Supplied",
    "name": "GOTHIC LIMITED",
    "sic_code_sic_text_2": "",
    "sic_code_sic_text_3": "",
    "sic_code_sic_text_4": "",
    "uid": "a3de056e-7b35-4bf7-82a7-ab882ea305b8",
    "created_at": "2025-11-04 14:15:49.846752",
    "registered_address_country": "TURKS AND CAICOS ISLANDS",
    "alpha_2_country_code_registered_address_country": "TC",
    "alpha_2_country_code_country_of_origin": "TC"
  },
  {
    "payload_uid": "c74df083-3d71-42da-963e-381b9b04b975",
    "number": "OE030633",
    "status": "Active",
    "category": "Overseas Entity",
    "country_of_origin": "TURKS AND CAICOS ISLANDS",
    "sic_code_sic_text_1": "None Supplied",
    "name": "JOCARL INVESTMENTS LTD.",
    "sic_code_sic_text_2": "",
    "sic_code_sic_text_3": "",
    "sic_code_sic_text_4": "",
    "uid": "e4748678-6066-4d54-a8ef-fa6e6791ba65",
    "created_at": "2025-11-04 14:15:49.846752",
    "registered_address_country": "TURKS AND CAICOS ISLANDS",
    "alpha_2_country_code_registered_address_country": "TC",
    "alpha_2_country_code_country_of_origin": "TC"
  },
  {
    "payload_uid": "c74df083-3d71-42da-963e-381b9b04b975",
    "number": "OE007619",
    "status": "Active",
    "category": "Overseas Entity",
    "country_of_origin": "TURKS AND CAICOS ISLANDS",
    "sic_code_sic_text_1": "None Supplied",
    "name": "LIBRIS LIMITED",
    "sic_code_sic_text_2": "",
    "sic_code_sic_text_3": "",
    "sic_code_sic_text_4": "",
    "uid": "8684fc52-b172-46b0-8c8e-24c9200f33f7",
    "created_at": "2025-11-04 14:15:49.846752",
    "registered_address_country": "TURKS AND CAICOS ISLANDS",
    "alpha_2_country_code_registered_address_country": "TC",
    "alpha_2_country_code_country_of_origin": "TC"
  },
  {
    "payload_uid": "c74df083-3d71-42da-963e-381b9b04b975",
    "number": "OE023852",
    "status": "Active",
    "category": "Overseas Entity",
    "country_of_origin": "TURKS AND CAICOS ISLANDS",
    "sic_code_sic_text_1": "None Supplied",
    "name": "METRIC INVESTMENTS LIMITED",
    "sic_code_sic_text_2": "",
    "sic_code_sic_text_3": "",
    "sic_code_sic_text_4": "",
    "uid": "0c8b0c67-0457-4b31-a48d-7580f4369cce",
    "created_at": "2025-11-04 14:15:49.846752",
    "registered_address_country": "TURKS AND CAICOS ISLANDS",
    "alpha_2_country_code_registered_address_country": "TC",
    "alpha_2_country_code_country_of_origin": "TC"
  },
  {
    "payload_uid": "c74df083-3d71-42da-963e-381b9b04b975",
    "number": "OE018616",
    "status": "Active",
    "category": "Overseas Entity",
    "country_of_origin": "TURKS AND CAICOS ISLANDS",
    "sic_code_sic_text_1": "None Supplied",
    "name": "MILLWAY HOLDINGS LTD",
    "sic_code_sic_text_2": "",
    "sic_code_sic_text_3": "",
    "sic_code_sic_text_4": "",
    "uid": "41e46aec-81e8-4c3e-b628-1c9f87b80d58",
    "created_at": "2025-11-04 14:15:49.846752",
    "registered_address_country": "TURKS AND CAICOS ISLANDS",
    "alpha_2_country_code_registered_address_country": "TC",
    "alpha_2_country_code_country_of_origin": "TC"
  },
  {
    "payload_uid": "c74df083-3d71-42da-963e-381b9b04b975",
    "number": "OE018105",
    "status": "Active",
    "category": "Overseas Entity",
    "country_of_origin": "TURKS AND CAICOS ISLANDS",
    "sic_code_sic_text_1": "None Supplied",
    "name": "MIRAMAR HOLDINGS SA",
    "sic_code_sic_text_2": "",
    "sic_code_sic_text_3": "",
    "sic_code_sic_text_4": "",
    "uid": "52e1a96c-7fdc-45db-8eee-1fc6f6e16486",
    "created_at": "2025-11-04 14:15:49.846752",
    "registered_address_country": "TURKS AND CAICOS ISLANDS",
    "alpha_2_country_code_registered_address_country": "TC",
    "alpha_2_country_code_country_of_origin": "TC"
  },
  {
    "payload_uid": "c74df083-3d71-42da-963e-381b9b04b975",
    "number": "OE029631",
    "status": "Active",
    "category": "Overseas Entity",
    "country_of_origin": "TURKS AND CAICOS ISLANDS",
    "sic_code_sic_text_1": "None Supplied",
    "name": "MUTTRAH LIMITED",
    "sic_code_sic_text_2": "",
    "sic_code_sic_text_3": "",
    "sic_code_sic_text_4": "",
    "uid": "f97b336d-fa9f-4d76-9f22-8d09dd83256c",
    "created_at": "2025-11-04 14:15:49.846752",
    "registered_address_country": "TURKS AND CAICOS ISLANDS",
    "alpha_2_country_code_registered_address_country": "TC",
    "alpha_2_country_code_country_of_origin": "TC"
  },
  {
    "payload_uid": "c74df083-3d71-42da-963e-381b9b04b975",
    "number": "OE034388",
    "status": "Active",
    "category": "Overseas Entity",
    "country_of_origin": "TURKS AND CAICOS ISLANDS",
    "sic_code_sic_text_1": "None Supplied",
    "name": "NORTH GLEN ESTATES LIMITED",
    "sic_code_sic_text_2": "",
    "sic_code_sic_text_3": "",
    "sic_code_sic_text_4": "",
    "uid": "268248a4-9518-4404-b341-924c5de6ce77",
    "created_at": "2025-11-04 14:15:49.846752",
    "registered_address_country": "TURKS AND CAICOS ISLANDS",
    "alpha_2_country_code_registered_address_country": "TC",
    "alpha_2_country_code_country_of_origin": "TC"
  },
  {
    "payload_uid": "c74df083-3d71-42da-963e-381b9b04b975",
    "number": "OE034103",
    "status": "Active",
    "category": "Overseas Entity",
    "country_of_origin": "TURKS AND CAICOS ISLANDS",
    "sic_code_sic_text_1": "None Supplied",
    "name": "ODYSSEY PTC LTD",
    "sic_code_sic_text_2": "",
    "sic_code_sic_text_3": "",
    "sic_code_sic_text_4": "",
    "uid": "e272937a-c520-4457-97db-18b38dc88e28",
    "created_at": "2025-11-04 14:15:49.846752",
    "registered_address_country": "TURKS AND CAICOS ISLANDS",
    "alpha_2_country_code_registered_address_country": "TC",
    "alpha_2_country_code_country_of_origin": "TC"
  },
  {
    "payload_uid": "c74df083-3d71-42da-963e-381b9b04b975",
    "number": "OE024180",
    "status": "Active",
    "category": "Overseas Entity",
    "country_of_origin": "TURKS AND CAICOS ISLANDS",
    "sic_code_sic_text_1": "None Supplied",
    "name": "PARK INVESTMENTS LIMITED",
    "sic_code_sic_text_2": "",
    "sic_code_sic_text_3": "",
    "sic_code_sic_text_4": "",
    "uid": "776e033f-791e-4059-be2e-fd66ca6e8cb0",
    "created_at": "2025-11-04 14:15:49.846752",
    "registered_address_country": "TURKS AND CAICOS ISLANDS",
    "alpha_2_country_code_registered_address_country": "TC",
    "alpha_2_country_code_country_of_origin": "TC"
  },
  {
    "payload_uid": "c74df083-3d71-42da-963e-381b9b04b975",
    "number": "OE028748",
    "status": "Active",
    "category": "Overseas Entity",
    "country_of_origin": "TURKS AND CAICOS ISLANDS",
    "sic_code_sic_text_1": "None Supplied",
    "name": "PARK PROPERTIES LTD.",
    "sic_code_sic_text_2": "",
    "sic_code_sic_text_3": "",
    "sic_code_sic_text_4": "",
    "uid": "5753eefa-7f6f-46ae-910a-5347aca58a0d",
    "created_at": "2025-11-04 14:15:49.846752",
    "registered_address_country": "TURKS AND CAICOS ISLANDS",
    "alpha_2_country_code_registered_address_country": "TC",
    "alpha_2_country_code_country_of_origin": "TC"
  },
  {
    "payload_uid": "c74df083-3d71-42da-963e-381b9b04b975",
    "number": "OE016354",
    "status": "Active",
    "category": "Overseas Entity",
    "country_of_origin": "TURKS AND CAICOS ISLANDS",
    "sic_code_sic_text_1": "None Supplied",
    "name": "PEMCO INVESTMENT LIMITED",
    "sic_code_sic_text_2": "",
    "sic_code_sic_text_3": "",
    "sic_code_sic_text_4": "",
    "uid": "5dbc4d75-e860-4e87-b99c-b545133148ec",
    "created_at": "2025-11-04 14:15:49.846752",
    "registered_address_country": "TURKS AND CAICOS ISLANDS",
    "alpha_2_country_code_registered_address_country": "TC",
    "alpha_2_country_code_country_of_origin": "TC"
  },
  {
    "payload_uid": "c74df083-3d71-42da-963e-381b9b04b975",
    "number": "OE019552",
    "status": "Active",
    "category": "Overseas Entity",
    "country_of_origin": "TURKS AND CAICOS ISLANDS",
    "sic_code_sic_text_1": "None Supplied",
    "name": "PICOLO HOLDINGS LIMITED",
    "sic_code_sic_text_2": "",
    "sic_code_sic_text_3": "",
    "sic_code_sic_text_4": "",
    "uid": "d985a533-ed33-4b02-a370-b1f5de3e241f",
    "created_at": "2025-11-04 14:15:49.846752",
    "registered_address_country": "TURKS AND CAICOS ISLANDS",
    "alpha_2_country_code_registered_address_country": "TC",
    "alpha_2_country_code_country_of_origin": "TC"
  },
  {
    "payload_uid": "c74df083-3d71-42da-963e-381b9b04b975",
    "number": "OE028684",
    "status": "Active",
    "category": "Overseas Entity",
    "country_of_origin": "TURKS AND CAICOS ISLANDS",
    "sic_code_sic_text_1": "None Supplied",
    "name": "REINA LIMITED",
    "sic_code_sic_text_2": "",
    "sic_code_sic_text_3": "",
    "sic_code_sic_text_4": "",
    "uid": "660696a2-e26d-452f-8f72-75ccee645c5c",
    "created_at": "2025-11-04 14:15:49.846752",
    "registered_address_country": "TURKS AND CAICOS ISLANDS",
    "alpha_2_country_code_registered_address_country": "TC",
    "alpha_2_country_code_country_of_origin": "TC"
  },
  {
    "payload_uid": "c74df083-3d71-42da-963e-381b9b04b975",
    "number": "OE031014",
    "status": "Active",
    "category": "Overseas Entity",
    "country_of_origin": "TURKS AND CAICOS ISLANDS",
    "sic_code_sic_text_1": "None Supplied",
    "name": "SATRE INVESTMENTS LIMITED",
    "sic_code_sic_text_2": "",
    "sic_code_sic_text_3": "",
    "sic_code_sic_text_4": "",
    "uid": "1902f84e-792a-46b0-a26f-a35f8e8e5578",
    "created_at": "2025-11-04 14:15:49.846752",
    "registered_address_country": "TURKS AND CAICOS ISLANDS",
    "alpha_2_country_code_registered_address_country": "TC",
    "alpha_2_country_code_country_of_origin": "TC"
  },
  {
    "payload_uid": "c74df083-3d71-42da-963e-381b9b04b975",
    "number": "OE005640",
    "status": "Active",
    "category": "Overseas Entity",
    "country_of_origin": "TURKS AND CAICOS ISLANDS",
    "sic_code_sic_text_1": "None Supplied",
    "name": "SENDARIA LIMITED",
    "sic_code_sic_text_2": "",
    "sic_code_sic_text_3": "",
    "sic_code_sic_text_4": "",
    "uid": "cc3c8b2d-0430-4f12-80c9-8e4daff2221a",
    "created_at": "2025-11-04 14:15:49.846752",
    "registered_address_country": "TURKS AND CAICOS ISLANDS",
    "alpha_2_country_code_registered_address_country": "TC",
    "alpha_2_country_code_country_of_origin": "TC"
  },
  {
    "payload_uid": "c74df083-3d71-42da-963e-381b9b04b975",
    "number": "OE032785",
    "status": "Active",
    "category": "Overseas Entity",
    "country_of_origin": "TURKS AND CAICOS ISLANDS",
    "sic_code_sic_text_1": "None Supplied",
    "name": "SILVER GROUP S.A.",
    "sic_code_sic_text_2": "",
    "sic_code_sic_text_3": "",
    "sic_code_sic_text_4": "",
    "uid": "f24e41d6-9976-4b5b-b253-ee6ad560453b",
    "created_at": "2025-11-04 14:15:49.846752",
    "registered_address_country": "TURKS AND CAICOS ISLANDS",
    "alpha_2_country_code_registered_address_country": "TC",
    "alpha_2_country_code_country_of_origin": "TC"
  },
  {
    "payload_uid": "c74df083-3d71-42da-963e-381b9b04b975",
    "number": "OE001016",
    "status": "Active",
    "category": "Overseas Entity",
    "country_of_origin": "TURKS AND CAICOS ISLANDS",
    "sic_code_sic_text_1": "None Supplied",
    "name": "SOUTHGATE HOLDINGS LIMITED",
    "sic_code_sic_text_2": "",
    "sic_code_sic_text_3": "",
    "sic_code_sic_text_4": "",
    "uid": "234cf815-8896-4ffc-bc66-bd6939f9faae",
    "created_at": "2025-11-04 14:15:49.846752",
    "registered_address_country": "TURKS AND CAICOS ISLANDS",
    "alpha_2_country_code_registered_address_country": "TC",
    "alpha_2_country_code_country_of_origin": "TC"
  },
  {
    "payload_uid": "c74df083-3d71-42da-963e-381b9b04b975",
    "number": "OE016137",
    "status": "Active",
    "category": "Overseas Entity",
    "country_of_origin": "TURKS AND CAICOS ISLANDS",
    "sic_code_sic_text_1": "None Supplied",
    "name": "SPINOLE LTD",
    "sic_code_sic_text_2": "",
    "sic_code_sic_text_3": "",
    "sic_code_sic_text_4": "",
    "uid": "b6102b88-7366-45fc-9fbb-c29589a67055",
    "created_at": "2025-11-04 14:15:49.846752",
    "registered_address_country": "TURKS AND CAICOS ISLANDS",
    "alpha_2_country_code_registered_address_country": "TC",
    "alpha_2_country_code_country_of_origin": "TC"
  },
  {
    "payload_uid": "c74df083-3d71-42da-963e-381b9b04b975",
    "number": "OE024166",
    "status": "Active",
    "category": "Overseas Entity",
    "country_of_origin": "TURKS AND CAICOS ISLANDS",
    "sic_code_sic_text_1": "None Supplied",
    "name": "ST GEORGE'S GROUP OF HOTELS LIMITED",
    "sic_code_sic_text_2": "",
    "sic_code_sic_text_3": "",
    "sic_code_sic_text_4": "",
    "uid": "ebbfbe36-f2b3-4312-873c-30399e9b8253",
    "created_at": "2025-11-04 14:15:49.846752",
    "registered_address_country": "TURKS AND CAICOS ISLANDS",
    "alpha_2_country_code_registered_address_country": "TC",
    "alpha_2_country_code_country_of_origin": "TC"
  },
  {
    "payload_uid": "c74df083-3d71-42da-963e-381b9b04b975",
    "number": "OE028510",
    "status": "Active",
    "category": "Overseas Entity",
    "country_of_origin": "TURKS AND CAICOS ISLANDS",
    "sic_code_sic_text_1": "None Supplied",
    "name": "STONEHAVEN PROPERTIES LIMITED",
    "sic_code_sic_text_2": "",
    "sic_code_sic_text_3": "",
    "sic_code_sic_text_4": "",
    "uid": "1584b0ab-7b40-47d3-8c91-4041ac0420af",
    "created_at": "2025-11-04 14:15:49.846752",
    "registered_address_country": "TURKS AND CAICOS ISLANDS",
    "alpha_2_country_code_registered_address_country": "TC",
    "alpha_2_country_code_country_of_origin": "TC"
  },
  {
    "payload_uid": "c74df083-3d71-42da-963e-381b9b04b975",
    "number": "SF000639",
    "status": "Active",
    "category": "Other company type",
    "country_of_origin": "TURKS & CAICOS ISLANDS",
    "sic_code_sic_text_1": "None Supplied",
    "name": "SUNRISE SYSTEMS (SCOTLAND)",
    "sic_code_sic_text_2": "",
    "sic_code_sic_text_3": "",
    "sic_code_sic_text_4": "",
    "uid": "662b8e5b-91e5-462c-b0bd-f2bad7d49468",
    "created_at": "2025-11-04 14:15:49.846752",
    "registered_address_country": "",
    "alpha_2_country_code_registered_address_country": null,
    "alpha_2_country_code_country_of_origin": "TC"
  },
  {
    "payload_uid": "c74df083-3d71-42da-963e-381b9b04b975",
    "number": "OE024164",
    "status": "Active",
    "category": "Overseas Entity",
    "country_of_origin": "TURKS AND CAICOS ISLANDS",
    "sic_code_sic_text_1": "None Supplied",
    "name": "TIRAV INVESTMENTS LIMITED",
    "sic_code_sic_text_2": "",
    "sic_code_sic_text_3": "",
    "sic_code_sic_text_4": "",
    "uid": "08770717-40f6-4ee5-9f3a-3234d5452ba1",
    "created_at": "2025-11-04 14:15:49.846752",
    "registered_address_country": "TURKS AND CAICOS ISLANDS",
    "alpha_2_country_code_registered_address_country": "TC",
    "alpha_2_country_code_country_of_origin": "TC"
  },
  {
    "payload_uid": "c74df083-3d71-42da-963e-381b9b04b975",
    "number": "OE025742",
    "status": "Active",
    "category": "Overseas Entity",
    "country_of_origin": "TURKS AND CAICOS ISLANDS",
    "sic_code_sic_text_1": "None Supplied",
    "name": "TRANCE LTD",
    "sic_code_sic_text_2": "",
    "sic_code_sic_text_3": "",
    "sic_code_sic_text_4": "",
    "uid": "9a724bf8-8c59-4aed-839b-eedd8d1b045b",
    "created_at": "2025-11-04 14:15:49.846752",
    "registered_address_country": "TURKS AND CAICOS ISLANDS",
    "alpha_2_country_code_registered_address_country": "TC",
    "alpha_2_country_code_country_of_origin": "TC"
  },
  {
    "payload_uid": "c74df083-3d71-42da-963e-381b9b04b975",
    "number": "OE030149",
    "status": "Active",
    "category": "Overseas Entity",
    "country_of_origin": "TURKS AND CAICOS ISLANDS",
    "sic_code_sic_text_1": "None Supplied",
    "name": "VAZ HOLDINGS LIMITED",
    "sic_code_sic_text_2": "",
    "sic_code_sic_text_3": "",
    "sic_code_sic_text_4": "",
    "uid": "5a4cf433-2640-4f58-a8da-4c6bae6a9617",
    "created_at": "2025-11-04 14:15:49.846752",
    "registered_address_country": "TURKS AND CAICOS ISLANDS",
    "alpha_2_country_code_registered_address_country": "TC",
    "alpha_2_country_code_country_of_origin": "TC"
  },
  {
    "payload_uid": "c74df083-3d71-42da-963e-381b9b04b975",
    "number": "OE008657",
    "status": "Active",
    "category": "Overseas Entity",
    "country_of_origin": "TURKS AND CAICOS ISLANDS",
    "sic_code_sic_text_1": "None Supplied",
    "name": "ZEEV LTD",
    "sic_code_sic_text_2": "",
    "sic_code_sic_text_3": "",
    "sic_code_sic_text_4": "",
    "uid": "5c7c8dce-dee9-43a2-bbd4-16f67ca671ef",
    "created_at": "2025-11-04 14:15:49.846752",
    "registered_address_country": "TURKS AND CAICOS ISLANDS",
    "alpha_2_country_code_registered_address_country": "TC",
    "alpha_2_country_code_country_of_origin": "TC"
  }
]
